Metadata-Version: 1.1
Name: type-classifier
Version: 0.0.1
Summary: ML classifier package
Home-page: https://github.com/pypa/sampleproject
Author: leowz
Author-email: weng.zhang@icloud.com
License: UNKNOWN
Platform: UNKNOWN
Classifier: Programming Language :: Python :: 3
Classifier: License :: OSI Approved :: MIT License
Classifier: Operating System :: OS Independent
